easyinput/__init__.py
marianoinput/__init__.py
marianoinput/previous/__init__.py
marianoinput/previous/penguin.py
marianoinput-0.0.6.dist-info/METADATA
marianoinput-0.0.6.dist-info/WHEEL
marianoinput-0.0.6.dist-info/top_level.txt
marianoinput-0.0.6.dist-info/RECORD
