Metadata-Version: 2.1
Name: marianoinput
Version: 0.0.6
Summary: Easily get valid numeric and boolean input from user
Author: Mariano Rico
Author-email: <marstab4@gmail.com>
Keywords: python,input
Classifier: Programming Language :: Python :: 3
Classifier: Operating System :: Unix
Classifier: Operating System :: MacOS :: MacOS X
Classifier: Operating System :: Microsoft :: Windows
